cleanlab/__init__.py
cleanlab/classification.py
cleanlab/count.py
cleanlab/data_valuation.py
cleanlab/dataset.py
cleanlab/filter.py
cleanlab/multiannotator.py
cleanlab/outlier.py
cleanlab/rank.py
cleanlab/typing.py
cleanlab/version.py
cleanlab/benchmarking/__init__.py
cleanlab/benchmarking/noise_generation.py
cleanlab/datalab/__init__.py
cleanlab/datalab/datalab.py
cleanlab/datalab/internal/__init__.py
cleanlab/datalab/internal/data.py
cleanlab/datalab/internal/data_issues.py
cleanlab/datalab/internal/display.py
cleanlab/datalab/internal/helper_factory.py
cleanlab/datalab/internal/issue_finder.py
cleanlab/datalab/internal/issue_manager_factory.py
cleanlab/datalab/internal/model_outputs.py
cleanlab/datalab/internal/report.py
cleanlab/datalab/internal/serialize.py
cleanlab/datalab/internal/spurious_correlation.py
cleanlab/datalab/internal/task.py
cleanlab/datalab/internal/adapter/__init__.py
cleanlab/datalab/internal/adapter/constants.py
cleanlab/datalab/internal/adapter/imagelab.py
cleanlab/datalab/internal/issue_manager/__init__.py
cleanlab/datalab/internal/issue_manager/data_valuation.py
cleanlab/datalab/internal/issue_manager/duplicate.py
cleanlab/datalab/internal/issue_manager/identifier_column.py
cleanlab/datalab/internal/issue_manager/imbalance.py
cleanlab/datalab/internal/issue_manager/issue_manager.py
cleanlab/datalab/internal/issue_manager/knn_graph_helpers.py
cleanlab/datalab/internal/issue_manager/label.py
cleanlab/datalab/internal/issue_manager/noniid.py
cleanlab/datalab/internal/issue_manager/null.py
cleanlab/datalab/internal/issue_manager/outlier.py
cleanlab/datalab/internal/issue_manager/underperforming_group.py
cleanlab/datalab/internal/issue_manager/multilabel/__init__.py
cleanlab/datalab/internal/issue_manager/multilabel/label.py
cleanlab/datalab/internal/issue_manager/regression/__init__.py
cleanlab/datalab/internal/issue_manager/regression/label.py
cleanlab/experimental/__init__.py
cleanlab/experimental/cifar_cnn.py
cleanlab-2.8.0.dist-info/LICENSE
cleanlab-2.8.0.dist-info/METADATA
cleanlab-2.8.0.dist-info/WHEEL
cleanlab-2.8.0.dist-info/top_level.txt
cleanlab-2.8.0.dist-info/RECORD
