Metadata-Version: 2.1
Name: cleanlab
Version: 2.8.0
Summary: The standard package for data-centric AI, machine learning with label errors, and automatically finding and fixing dataset issues in Python.
Author-email: "Cleanlab Inc." <team@cleanlab.ai>
License: Apache License
Project-URL: Homepage, https://cleanlab.ai
Project-URL: Documentation, https://docs.cleanlab.ai
Project-URL: Bug Tracker, https://github.com/cleanlab/cleanlab/issues
Project-URL: Source Code, https://github.com/cleanlab/cleanlab
Keywords: machine_learning,data_cleaning,confident_learning,classification,weak_supervision,learning_with_noisy_labels,unsupervised_learning,datacentric_ai,datacentric
Classifier: Development Status :: 4 - Beta
Classifier: Intended Audience :: Developers
Classifier: Intended Audience :: Education
Classifier: Intended Audience :: Science/Research
Classifier: Intended Audience :: Information Technology
Classifier: Natural Language :: English
Classifier: Programming Language :: Python :: 3
Classifier: Programming Language :: Python :: 3.10
Classifier: Programming Language :: Python :: 3.11
Classifier: Programming Language :: Python :: 3.12
Classifier: Programming Language :: Python :: 3.13
Classifier: Programming Language :: Python :: 3.14
Classifier: Programming Language :: Python
Classifier: Topic :: Software Development
Classifier: Topic :: Scientific/Engineering
Classifier: Topic :: Scientific/Engineering :: Mathematics
Classifier: Topic :: Scientific/Engineering :: Artificial Intelligence
Classifier: Topic :: Software Development :: Libraries
Classifier: Topic :: Software Development :: Libraries :: Python Modules
Requires-Python: >=3.10
License-File: LICENSE
Requires-Dist: numpy>=1.22
Requires-Dist: scikit-learn>=1.1
Requires-Dist: tqdm>=4.53.0
Requires-Dist: pandas>=1.4.0
Requires-Dist: termcolor>=2.4.0
Provides-Extra: all
Requires-Dist: matplotlib>=3.5.1; extra == "all"
Requires-Dist: cleanvision>=0.3.6; extra == "all"
Requires-Dist: datasets>=2.7.0; extra == "all"
Provides-Extra: datalab
Requires-Dist: datasets>=2.7.0; extra == "datalab"
Provides-Extra: image
Requires-Dist: datasets>=2.7.0; extra == "image"
Requires-Dist: cleanvision>=0.3.6; extra == "image"
